api_selectel/__init__.py
api_selectel/api_selectel.py
api_selectel-0.1.1.dist-info/METADATA
api_selectel-0.1.1.dist-info/WHEEL
api_selectel-0.1.1.dist-info/top_level.txt
api_selectel-0.1.1.dist-info/RECORD
