Metadata-Version: 2.1
Name: api-selectel
Version: 0.1.1
Summary: A selectel api package
Author-email: Artem Gnatyuk <temskiy@gmail.com>
Project-URL: Homepage, https://gitlab.com/temskiy/selectel_api
Classifier: Programming Language :: Python :: 3
Classifier: Operating System :: OS Independent
Requires-Python: >=3.6
Requires-Dist: Jinja2 (>=2.10)
Requires-Dist: requests (>=2.18.4)
